odoo/addons/purchase_stock_analytic/README.rst
odoo/addons/purchase_stock_analytic/__init__.py
odoo/addons/purchase_stock_analytic/__manifest__.py
odoo/addons/purchase_stock_analytic/i18n/purchase_stock_analytic.pot
odoo/addons/purchase_stock_analytic/models/__init__.py
odoo/addons/purchase_stock_analytic/models/purchase_order_line.py
odoo/addons/purchase_stock_analytic/static/description/icon.png
odoo/addons/purchase_stock_analytic/tests/__init__.py
odoo/addons/purchase_stock_analytic/tests/test_purchase_stock_analytic.py
odoo13_addon_purchase_stock_analytic-13.0.1.0.1.dev3.dist-info/METADATA
odoo13_addon_purchase_stock_analytic-13.0.1.0.1.dev3.dist-info/WHEEL
odoo13_addon_purchase_stock_analytic-13.0.1.0.1.dev3.dist-info/top_level.txt
odoo13_addon_purchase_stock_analytic-13.0.1.0.1.dev3.dist-info/RECORD
